puyaisp/puyaisp.py
puyaisp-1.4.1.dist-info/LICENSE
puyaisp-1.4.1.dist-info/METADATA
puyaisp-1.4.1.dist-info/WHEEL
puyaisp-1.4.1.dist-info/entry_points.txt
puyaisp-1.4.1.dist-info/top_level.txt
puyaisp-1.4.1.dist-info/RECORD
