Metadata-Version: 2.1
Name: puyaisp
Version: 1.4.1
Summary: Programming Tool for PUYA PY32F0xx Microcontrollers
Author-email: Stefan Wagner <wagiminator@web.de>
Maintainer-email: Stefan Wagner <wagiminator@web.de>
License: MIT License
Project-URL: Homepage, https://wagiminator.github.io/
Project-URL: Repository, https://github.com/wagiminator/MCU-Flash-Tools
Project-URL: Issues, https://github.com/wagiminator/MCU-Flash-Tools/issues
Keywords: ISP,PUYA,PY32F002A,PY32F003,PY32F030,microcontroller
Classifier: Development Status :: 5 - Production/Stable
Classifier: Programming Language :: Python :: 3
Classifier: License :: OSI Approved :: MIT License
Classifier: Operating System :: OS Independent
Classifier: Intended Audience :: Developers
Classifier: Topic :: Software Development :: Embedded Systems
Requires-Python: >=3.8
License-File: LICENSE
Requires-Dist: pyserial
